quack_norris/__init__.py
quack_norris/__main__.py
quack_norris/__ui_without_terminal__.py
quack_norris/common/__init__.py
quack_norris/common/_types.py
quack_norris/common/config.py
quack_norris/common/llm_provider.py
quack_norris/configs/server.json
quack_norris/configs/ui.json
quack_norris/server/__init__.py
quack_norris/server/api_server.py
quack_norris/server/router.py
quack_norris/server/user.py
quack_norris/server/tools/__init__.py
quack_norris/ui/__init__.py
quack_norris/ui/app.py
quack_norris/ui/assets/icons/duck.png
quack_norris/ui/assets/icons/duck_low_res.png
quack_norris/ui/models/__init__.py
quack_norris/ui/models/chat_state.py
quack_norris/ui/views/__init__.py
quack_norris/ui/views/chat_view.py
quack_norris/ui/views/launcher.py
quack_norris/ui/views/components/__init__.py
quack_norris-0.0.1.dist-info/METADATA
quack_norris-0.0.1.dist-info/WHEEL
quack_norris-0.0.1.dist-info/entry_points.txt
quack_norris-0.0.1.dist-info/licenses/LICENSE
quack_norris-0.0.1.dist-info/RECORD
