Metadata-Version: 2.4
Name: quack-norris
Version: 0.0.1
Summary: Your AImazing rubber duck debugging companion. Helps you with anything on your PC.
Author: Michael Fuerst
Maintainer: Michael Fuerst
License-Expression: MIT
License-File: LICENSE
Keywords: agentic,ai,assistant,debugging,norris,quack,rubber duck
Requires-Python: >=3.9
Requires-Dist: flask>=3.1.0
Requires-Dist: openai>=1.59.7
Requires-Dist: pillow>=11.0.0
Requires-Dist: pypdf>=5.1.0
Requires-Dist: setproctitle>=1.3.4
Requires-Dist: tqdm>=4.67.1
Requires-Dist: waitress>=3.0.2
Provides-Extra: dev
Requires-Dist: flake8>=7.1.1; extra == 'dev'
Requires-Dist: pytest>=8.3.4; extra == 'dev'
Provides-Extra: ui
Requires-Dist: mss>=9.0.2; extra == 'ui'
Requires-Dist: pyside6>=6.8.0.1; extra == 'ui'
